{
"type": "FeatureCollection",
"name": "out",
"crs": { "type": "name", "properties": { "name": "urn:ogc:def:crs:EPSG::4269" } },
"features": [
{ "type": "Feature", "properties": { "STATEFP": "78", "PLACEFP": "16300", "PLACENS": "02414184", "GEOID": "7816300", "NAME": "Charlotte Amalie", "NAMELSAD": "Charlotte Amalie town", "LSAD": "43", "CLASSFP": "C9", "PCICBSA": "N", "PCINECTA": "N", "MTFCC": "G4110", "FUNCSTAT": "N", "ALAND": 3145266, "AWATER": 0, "INTPTLAT": "+18.3418993", "INTPTLON": "-064.9331546" }, "geometry": { "type": "Polygon", "coordinates": [ [ [ -64.948122, 18.345433 ], [ -64.943552, 18.344925 ], [ -64.930634, 18.348861 ], [ -64.921701, 18.348301 ], [ -64.922464, 18.343972 ], [ -64.921109, 18.341427 ], [ -64.91466, 18.33854 ], [ -64.919393, 18.334559 ], [ -64.926735, 18.340007 ], [ -64.929855, 18.339293 ], [ -64.931163, 18.340518 ], [ -64.939618, 18.338351 ], [ -64.940518, 18.334483 ], [ -64.944736, 18.333702 ], [ -64.947268, 18.33587 ], [ -64.948122, 18.345433 ] ] ] } },
{ "type": "Feature", "properties": { "STATEFP": "78", "PLACEFP": "19900", "PLACENS": "02414185", "GEOID": "7819900", "NAME": "Christiansted", "NAMELSAD": "Christiansted town", "LSAD": "43", "CLASSFP": "C9", "PCICBSA": "N", "PCINECTA": "N", "MTFCC": "G4110", "FUNCSTAT": "N", "ALAND": 1331653, "AWATER": 0, "INTPTLAT": "+17.7439296", "INTPTLON": "-064.7063739" }, "geometry": { "type": "Polygon", "coordinates": [ [ [ -64.71626, 17.74531 ], [ -64.711419, 17.74879 ], [ -64.708762, 17.746861 ], [ -64.701735, 17.747435 ], [ -64.699532, 17.745592 ], [ -64.698132, 17.747863 ], [ -64.695674, 17.741622 ], [ -64.69851, 17.740922 ], [ -64.699092, 17.742519 ], [ -64.70121, 17.74257 ], [ -64.7085, 17.739253 ], [ -64.713374, 17.739709 ], [ -64.712588, 17.742025 ], [ -64.71626, 17.74531 ] ] ] } },
{ "type": "Feature", "properties": { "STATEFP": "78", "PLACEFP": "37900", "PLACENS": "02414186", "GEOID": "7837900", "NAME": "Frederiksted", "NAMELSAD": "Frederiksted town", "LSAD": "43", "CLASSFP": "C9", "PCICBSA": "N", "PCINECTA": "N", "MTFCC": "G4110", "FUNCSTAT": "N", "ALAND": 440635, "AWATER": 47112, "INTPTLAT": "+17.7129077", "INTPTLON": "-064.8822745" }, "geometry": { "type": "Polygon", "coordinates": [ [ [ -64.89038, 17.71402 ], [ -64.884003, 17.71449 ], [ -64.883129, 17.716619 ], [ -64.88131, 17.71461 ], [ -64.879496, 17.714841 ], [ -64.8772, 17.71125 ], [ -64.880057, 17.708202 ], [ -64.883741, 17.708274 ], [ -64.883919, 17.713887 ], [ -64.89038, 17.71402 ] ] ] } },
{ "type": "Feature", "properties": { "STATEFP": "78", "PLACEFP": "18100", "PLACENS": "02414007", "GEOID": "7818100", "NAME": "Charlotte Amalie East", "NAMELSAD": "Charlotte Amalie East CDP", "LSAD": "57", "CLASSFP": "U2", "PCICBSA": "N", "PCINECTA": "N", "MTFCC": "G4210", "FUNCSTAT": "S", "ALAND": 863636, "AWATER": 0, "INTPTLAT": "+18.3339734", "INTPTLON": "-064.9157318" }, "geometry": { "type": "Polygon", "coordinates": [ [ [ -64.926506, 18.3303 ], [ -64.91466, 18.33854 ], [ -64.9098, 18.33798 ], [ -64.910219, 18.332034 ], [ -64.91939, 18.329852 ], [ -64.92158, 18.33138 ], [ -64.923007, 18.32995 ], [ -64.924768, 18.331162 ], [ -64.926506, 18.3303 ] ] ] } },
{ "type": "Feature", "properties": { "STATEFP": "78", "PLACEFP": "19000", "PLACENS": "02414008", "GEOID": "7819000", "NAME": "Charlotte Amalie West", "NAMELSAD": "Charlotte Amalie West CDP", "LSAD": "57", "CLASSFP": "U2", "PCICBSA": "N", "PCINECTA": "N", "MTFCC": "G4210", "FUNCSTAT": "S", "ALAND": 5113188, "AWATER": 27768, "INTPTLAT": "+18.3367072", "INTPTLON": "-064.9720769" }, "geometry": { "type": "Polygon", "coordinates": [ [ [ -64.984176, 18.337584 ], [ -64.975325, 18.338508 ], [ -64.97792, 18.339364 ], [ -64.976338, 18.343464 ], [ -64.974767, 18.341707 ], [ -64.972948, 18.346589 ], [ -64.961663, 18.348857 ], [ -64.95988, 18.34614 ], [ -64.948122, 18.345433 ], [ -64.947268, 18.33587 ], [ -64.954625, 18.332302 ], [ -64.951903, 18.331491 ], [ -64.955008, 18.331248 ], [ -64.955134, 18.328427 ], [ -64.95689, 18.327209 ], [ -64.959435, 18.32797 ], [ -64.9608, 18.330175 ], [ -64.9599, 18.332016 ], [ -64.961258, 18.332497 ], [ -64.961707, 18.325334 ], [ -64.963524, 18.324349 ], [ -64.965578, 18.327146 ], [ -64.963503, 18.333938 ], [ -64.964489, 18.335298 ], [ -64.969465, 18.335124 ], [ -64.969534, 18.332107 ], [ -64.972052, 18.329082 ], [ -64.97477, 18.3353 ], [ -64.983372, 18.33533 ], [ -64.984176, 18.337584 ] ] ] } },
{ "type": "Feature", "properties": { "STATEFP": "78", "PLACEFP": "27000", "PLACENS": "02651573", "GEOID": "7827000", "NAME": "Coral Bay", "NAMELSAD": "Coral Bay CDP", "LSAD": "57", "CLASSFP": "U1", "PCICBSA": "N", "PCINECTA": "N", "MTFCC": "G4210", "FUNCSTAT": "S", "ALAND": 4757016, "AWATER": 975009, "INTPTLAT": "+18.3451896", "INTPTLON": "-064.7172899" }, "geometry": { "type": "Polygon", "coordinates": [ [ [ -64.732613, 18.352368 ], [ -64.72883, 18.356749 ], [ -64.723962, 18.35749 ], [ -64.717698, 18.356301 ], [ -64.714081, 18.353186 ], [ -64.709521, 18.353824 ], [ -64.705079, 18.350199 ], [ -64.708647, 18.344768 ], [ -64.707242, 18.341239 ], [ -64.705213, 18.340446 ], [ -64.707651, 18.335132 ], [ -64.700464, 18.330629 ], [ -64.709284, 18.326545 ], [ -64.710232, 18.328851 ], [ -64.713114, 18.329487 ], [ -64.716082, 18.336977 ], [ -64.720224, 18.335764 ], [ -64.72665, 18.341026 ], [ -64.724912, 18.34346 ], [ -64.731742, 18.345911 ], [ -64.731029, 18.350405 ], [ -64.729006, 18.35096 ], [ -64.732613, 18.352368 ] ] ] } },
{ "type": "Feature", "properties": { "STATEFP": "78", "PLACEFP": "28000", "PLACENS": "02414009", "GEOID": "7828000", "NAME": "Cruz Bay", "NAMELSAD": "Cruz Bay CDP", "LSAD": "57", "CLASSFP": "U1", "PCICBSA": "N", "PCINECTA": "N", "MTFCC": "G4210", "FUNCSTAT": "S", "ALAND": 7870102, "AWATER": 2465481, "INTPTLAT": "+18.3237480", "INTPTLON": "-064.7797895" }, "geometry": { "type": "Polygon", "coordinates": [ [ [ -64.799794, 18.326681 ], [ -64.798973, 18.336864 ], [ -64.795578, 18.338606 ], [ -64.79161, 18.339898 ], [ -64.7839, 18.335863 ], [ -64.77614, 18.336547 ], [ -64.776102, 18.337928 ], [ -64.769706, 18.339825 ], [ -64.769698, 18.331 ], [ -64.764583, 18.329683 ], [ -64.759925, 18.326328 ], [ -64.756316, 18.326182 ], [ -64.756271, 18.316591 ], [ -64.765977, 18.31055 ], [ -64.781459, 18.31053 ], [ -64.78474, 18.313445 ], [ -64.791205, 18.314449 ], [ -64.795936, 18.324613 ], [ -64.799794, 18.326681 ] ] ] } },
{ "type": "Feature", "properties": { "STATEFP": "78", "PLACEFP": "39700", "PLACENS": "02414020", "GEOID": "7839700", "NAME": "Frederiksted Southeast", "NAMELSAD": "Frederiksted Southeast CDP", "LSAD": "57", "CLASSFP": "U2", "PCICBSA": "N", "PCINECTA": "N", "MTFCC": "G4210", "FUNCSTAT": "S", "ALAND": 2617377, "AWATER": 0, "INTPTLAT": "+17.7030250", "INTPTLON": "-064.8763337" }, "geometry": { "type": "Polygon", "coordinates": [ [ [ -64.885682, 17.701939 ], [ -64.883741, 17.708274 ], [ -64.880057, 17.708202 ], [ -64.87567, 17.7114 ], [ -64.86743, 17.707 ], [ -64.86476, 17.70056 ], [ -64.885168, 17.693982 ], [ -64.884586, 17.701134 ], [ -64.885682, 17.701939 ] ] ] } },
{ "type": "Feature", "properties": { "STATEFP": "78", "PLACEFP": "65530", "PLACENS": "02651575", "GEOID": "7865530", "NAME": "Red Hook", "NAMELSAD": "Red Hook CDP", "LSAD": "57", "CLASSFP": "U2", "PCICBSA": "N", "PCINECTA": "N", "MTFCC": "G4210", "FUNCSTAT": "S", "ALAND": 733481, "AWATER": 716141, "INTPTLAT": "+18.3243646", "INTPTLON": "-064.8489221" }, "geometry": { "type": "Polygon", "coordinates": [ [ [ -64.857592, 18.323041 ], [ -64.84763, 18.332586 ], [ -64.831833, 18.324764 ], [ -64.83727, 18.32586 ], [ -64.84622, 18.32203 ], [ -64.847806, 18.324717 ], [ -64.849689, 18.32266 ], [ -64.85431, 18.32148 ], [ -64.857592, 18.323041 ] ] ] } },
{ "type": "Feature", "properties": { "STATEFP": "78", "PLACEFP": "78300", "PLACENS": "02413996", "GEOID": "7878300", "NAME": "Tutu", "NAMELSAD": "Tutu CDP", "LSAD": "57", "CLASSFP": "U1", "PCICBSA": "N", "PCINECTA": "N", "MTFCC": "G4210", "FUNCSTAT": "S", "ALAND": 4296306, "AWATER": 28670, "INTPTLAT": "+18.3390198", "INTPTLON": "-064.8885716" }, "geometry": { "type": "Polygon", "coordinates": [ [ [ -64.90364, 18.34551 ], [ -64.90215, 18.34769 ], [ -64.88482, 18.34994 ], [ -64.87837, 18.34435 ], [ -64.871472, 18.335085 ], [ -64.88046, 18.335385 ], [ -64.885288, 18.331542 ], [ -64.88842, 18.331147 ], [ -64.887976, 18.32994 ], [ -64.894333, 18.331297 ], [ -64.894333, 18.333928 ], [ -64.89877, 18.33505 ], [ -64.89848, 18.33992 ], [ -64.90364, 18.34551 ] ] ] } }
]
}
